stdresponse/__init__.py
stdresponse/response.py
stdresponse-0.1.1.dist-info/licenses/LICENSE
stdresponse-0.1.1.dist-info/METADATA
stdresponse-0.1.1.dist-info/WHEEL
stdresponse-0.1.1.dist-info/top_level.txt
stdresponse-0.1.1.dist-info/RECORD
